Metadata-Version: 1.1
Name: qauto.makefile
Version: 0.0.1
Summary: Makefile - test runner
Home-page: UNKNOWN
Author: QA Automation
Author-email: UNKNOWN
License: UNKNOWN
Platform: UNKNOWN
Classifier: Programming Language :: Python :: 3
